docx_editor/__init__.py
docx_editor/comments.py
docx_editor/document.py
docx_editor/exceptions.py
docx_editor/track_changes.py
docx_editor/workspace.py
docx_editor/xml_editor.py
docx_editor/ooxml/__init__.py
docx_editor/ooxml/pack.py
docx_editor/ooxml/unpack.py
docx_editor/ooxml/templates/comments.xml
docx_editor/ooxml/templates/commentsExtended.xml
docx_editor/ooxml/templates/commentsExtensible.xml
docx_editor/ooxml/templates/commentsIds.xml
docx_editor/ooxml/templates/people.xml
docx_editor-0.1.1.dist-info/METADATA
docx_editor-0.1.1.dist-info/WHEEL
docx_editor-0.1.1.dist-info/licenses/LICENSE
docx_editor-0.1.1.dist-info/RECORD
