Metadata-Version: 2.4
Name: docx-editor
Version: 0.1.1
Summary: Edit docx with python
Project-URL: Homepage, https://pablospe.github.io/docx-editor/
Project-URL: Repository, https://github.com/pablospe/docx-editor
Project-URL: Documentation, https://pablospe.github.io/docx-editor/
Author-email: Pablo Speciale <pablospe@users.noreply.github.com>
License-File: LICENSE
Keywords: python
Classifier: Intended Audience :: Developers
Classifier: Programming Language :: Python
Classifier: Programming Language :: Python :: 3
Classifier: Programming Language :: Python :: 3.10
Classifier: Programming Language :: Python :: 3.11
Classifier: Programming Language :: Python :: 3.12
Classifier: Programming Language :: Python :: 3.13
Classifier: Programming Language :: Python :: 3.14
Classifier: Topic :: Software Development :: Libraries :: Python Modules
Requires-Python: <4.0,>=3.10
Requires-Dist: defusedxml>=0.7.1
